mongo_pipebuilder/__init__.py
mongo_pipebuilder/builder.py
mongo_pipebuilder-0.3.1.dist-info/licenses/LICENSE
mongo_pipebuilder-0.3.1.dist-info/METADATA
mongo_pipebuilder-0.3.1.dist-info/WHEEL
mongo_pipebuilder-0.3.1.dist-info/top_level.txt
mongo_pipebuilder-0.3.1.dist-info/RECORD
