Metadata-Version: 2.4
Name: mongo-pipebuilder
Version: 0.3.1
Summary: Type-safe, fluent MongoDB aggregation pipeline builder
Author-email: seligoroff <seligoroff@gmail.com>
License: MIT
Project-URL: Homepage, https://github.com/seligoroff/mongo-pipebuilder
Project-URL: Documentation, https://github.com/seligoroff/mongo-pipebuilder#readme
Project-URL: Repository, https://github.com/seligoroff/mongo-pipebuilder
Project-URL: Issues, https://github.com/seligoroff/mongo-pipebuilder/issues
Keywords: mongodb,aggregation,pipeline,builder,query
Classifier: Development Status :: 3 - Alpha
Classifier: Intended Audience :: Developers
Classifier: License :: OSI Approved :: MIT License
Classifier: Programming Language :: Python :: 3
Classifier: Programming Language :: Python :: 3.8
Classifier: Programming Language :: Python :: 3.9
Classifier: Programming Language :: Python :: 3.10
Classifier: Programming Language :: Python :: 3.11
Classifier: Programming Language :: Python :: 3.12
Classifier: Topic :: Database
Classifier: Topic :: Software Development :: Libraries :: Python Modules
Requires-Python: >=3.8
License-File: LICENSE
Requires-Dist: typing_extensions>=4.0.0; python_version < "3.11"
Dynamic: license-file
